<?xml version="1.0" encoding="utf-8"?>
<projectiles>
	<!-- projectile itself defines its slot, 0 being actual throwables that can also equipped, thrown, bought and found -->
	<!-- mortar shell is in slot 2 -->
	<projectile file="mortar_shell.projectile" />
	<projectile file="artillery_shell.projectile" />

	<!-- CABAL PROJECTILES -->
	<projectile file="player_grenade.projectile" />
	<projectile file="cabal_grenade.projectile" />

	<!-- FACTION-SPECIFIC THROWABLES -->
	<!-- Player throwables -->
	<!-- end Player throwables -->
	<!-- Cabal throwables -->
	<!-- end Cabal throwables -->

	<!-- END CABAL PROJECTILES -->

	<projectile file="flare.projectile" />
 	<projectile file="flare_checkpoint.projectile" />
	<projectile file="debri_stun.projectile" />
	<projectile file="debri_stun_medium.projectile" />
	<projectile file="debri_stun_big.projectile" />
	<projectile file="debri_destroy_big.projectile" />
	<projectile file="debri_destroy_small.projectile" />

</projectiles>
